plocate/__init__.py
plocate/cli.py
plocate/mlocatedb.py
plocate/plocate.py
plocate/utils.py
plocate-0.1.2.dist-info/DESCRIPTION.rst
plocate-0.1.2.dist-info/METADATA
plocate-0.1.2.dist-info/RECORD
plocate-0.1.2.dist-info/WHEEL
plocate-0.1.2.dist-info/entry_points.txt
plocate-0.1.2.dist-info/metadata.json
plocate-0.1.2.dist-info/top_level.txt
