Metadata-Version: 2.0
Name: plocate
Version: 0.1.2
Summary: Locate implementation with extra filtering features, compatible with mlocate.db format.
Home-page: https://github.com/Aetf/plocate
Author: Aetf
Author-email: aetf@unlimitedcodeworks.xyz
License: BSD license
Keywords: plocate
Platform: UNKNOWN
Classifier: Development Status :: 2 - Pre-Alpha
Classifier: Intended Audience :: Developers
Classifier: License :: OSI Approved :: BSD License
Classifier: Natural Language :: English
Classifier: Programming Language :: Python :: 2
Classifier: Programming Language :: Python :: 2.6
Classifier: Programming Language :: Python :: 2.7
Classifier: Programming Language :: Python :: 3
Classifier: Programming Language :: Python :: 3.3
Classifier: Programming Language :: Python :: 3.4
Classifier: Programming Language :: Python :: 3.5
Requires-Dist: Click (==6.6)
Requires-Dist: future (==0.15.2)
